{
  "scriptId": "334",
  "url": "file:///Users/tettuan/github/breakdownlogger/tests/log_filter_test.ts",
  "functions": [
    {
      "functionName": "",
      "ranges": [{ "startOffset": 0, "endOffset": 3464, "count": 1 }],
      "isBlockCoverage": true
    },
    {
      "functionName": "",
      "ranges": [{ "startOffset": 200, "endOffset": 3461, "count": 1 }],
      "isBlockCoverage": true
    },
    {
      "functionName": "",
      "ranges": [{ "startOffset": 248, "endOffset": 1046, "count": 1 }],
      "isBlockCoverage": true
    },
    {
      "functionName": "",
      "ranges": [{ "startOffset": 361, "endOffset": 543, "count": 1 }],
      "isBlockCoverage": true
    },
    {
      "functionName": "",
      "ranges": [{ "startOffset": 608, "endOffset": 710, "count": 1 }],
      "isBlockCoverage": true
    },
    {
      "functionName": "",
      "ranges": [{ "startOffset": 770, "endOffset": 874, "count": 1 }],
      "isBlockCoverage": true
    },
    {
      "functionName": "",
      "ranges": [{ "startOffset": 931, "endOffset": 1040, "count": 1 }],
      "isBlockCoverage": true
    },
    {
      "functionName": "",
      "ranges": [{ "startOffset": 1090, "endOffset": 2133, "count": 1 }],
      "isBlockCoverage": true
    },
    {
      "functionName": "",
      "ranges": [{ "startOffset": 1207, "endOffset": 1300, "count": 1 }],
      "isBlockCoverage": true
    },
    {
      "functionName": "",
      "ranges": [{ "startOffset": 1369, "endOffset": 1504, "count": 1 }],
      "isBlockCoverage": true
    },
    {
      "functionName": "",
      "ranges": [{ "startOffset": 1575, "endOffset": 1716, "count": 1 }],
      "isBlockCoverage": true
    },
    {
      "functionName": "",
      "ranges": [{ "startOffset": 1770, "endOffset": 1921, "count": 1 }],
      "isBlockCoverage": true
    },
    {
      "functionName": "",
      "ranges": [{ "startOffset": 1977, "endOffset": 2127, "count": 1 }],
      "isBlockCoverage": true
    },
    {
      "functionName": "",
      "ranges": [{ "startOffset": 2191, "endOffset": 3457, "count": 1 }],
      "isBlockCoverage": true
    },
    {
      "functionName": "",
      "ranges": [
        { "startOffset": 2340, "endOffset": 2956, "count": 1 },
        { "startOffset": 2802, "endOffset": 2879, "count": 0 }
      ],
      "isBlockCoverage": true
    },
    {
      "functionName": "",
      "ranges": [
        { "startOffset": 3043, "endOffset": 3451, "count": 1 },
        { "startOffset": 3360, "endOffset": 3437, "count": 0 }
      ],
      "isBlockCoverage": true
    }
  ]
}
